browserness/__init__.py
browserness/client.py
browserness/environment.py
browserness/browsers/__init__.py
browserness/browsers/client.py
browserness/browsers/raw_client.py
browserness/core/__init__.py
browserness/core/api_error.py
browserness/core/client_wrapper.py
browserness/core/datetime_utils.py
browserness/core/file.py
browserness/core/force_multipart.py
browserness/core/http_client.py
browserness/core/http_response.py
browserness/core/jsonable_encoder.py
browserness/core/pydantic_utilities.py
browserness/core/query_encoder.py
browserness/core/remove_none_from_dict.py
browserness/core/request_options.py
browserness/core/serialization.py
browserness/errors/__init__.py
browserness/errors/unprocessable_entity_error.py
browserness/health/__init__.py
browserness/health/client.py
browserness/health/raw_client.py
browserness/resources/__init__.py
browserness/resources/client.py
browserness/resources/raw_client.py
browserness/tokens/__init__.py
browserness/tokens/client.py
browserness/tokens/raw_client.py
browserness/types/__init__.py
browserness/types/browser_list_response.py
browserness/types/browser_response_model.py
browserness/types/delete_response.py
browserness/types/health_check_response.py
browserness/types/health_status.py
browserness/types/http_validation_error.py
browserness/types/validation_error.py
browserness/types/validation_error_loc_item.py
browserness-0.0.3.dist-info/licenses/LICENSE
browserness-0.0.3.dist-info/METADATA
browserness-0.0.3.dist-info/WHEEL
browserness-0.0.3.dist-info/top_level.txt
browserness-0.0.3.dist-info/RECORD
