Metadata-Version: 2.4
Name: browserness
Version: 0.0.3
Summary: Python SDK for Browserness API
Home-page: https://github.com/browserness/sdk-python
Author: Browserness
Author-email: Browserness <support@browserness.com>
License: MIT
Project-URL: Homepage, https://github.com/browserness/sdk-python
Project-URL: Repository, https://github.com/browserness/sdk-python
Project-URL: Documentation, https://api.browserness.com/docs
Classifier: Development Status :: 4 - Beta
Classifier: Intended Audience :: Developers
Classifier: License :: OSI Approved :: MIT License
Classifier: Operating System :: OS Independent
Classifier: Programming Language :: Python :: 3
Classifier: Programming Language :: Python :: 3.8
Classifier: Programming Language :: Python :: 3.9
Classifier: Programming Language :: Python :: 3.10
Classifier: Programming Language :: Python :: 3.11
Classifier: Programming Language :: Python :: 3.12
Requires-Python: >=3.8
License-File: LICENSE
Requires-Dist: httpx>=0.23.0
Requires-Dist: pydantic<3,>=1.9.0
Dynamic: author
Dynamic: home-page
Dynamic: license-file
Dynamic: requires-python
